ac_library_python_stubs-0.1.0.20250812.dist-info/licenses/LICENSE
atcoder/py.typed
atcoder-stubs/__init__.py
atcoder-stubs/convolution.pyi
atcoder-stubs/fenwicktree.pyi
atcoder-stubs/lazysegtree.pyi
atcoder-stubs/py.typed
atcoder-stubs/segtree.pyi
ac_library_python_stubs-0.1.0.20250812.dist-info/METADATA
ac_library_python_stubs-0.1.0.20250812.dist-info/WHEEL
ac_library_python_stubs-0.1.0.20250812.dist-info/top_level.txt
ac_library_python_stubs-0.1.0.20250812.dist-info/RECORD
