Metadata-Version: 2.4
Name: ac-library-python-stubs
Version: 0.1.0.20250812
Summary: Type stubs for not522/ac-library-python
Author-email: kairi003 <kairi.satellite@gmail.com>
Project-URL: Homepage, https://github.com/kairi003/ac-library-python-stubs
Project-URL: Repository, https://github.com/kairi003/ac-library-python-stubs.git
Requires-Python: >=3.9
License-File: LICENSE
Requires-Dist: ac-library-python==0.1.0
Dynamic: license-file
